[
    {
        "page": "4833_1",
        "type": "桌面类",
        "name": "台球 lunar pool",
        "url": "4833_1.nes",
        "desc": "任天堂美洲公司，一款台球nes游戏，界面是经过中文汉化的。",
        "icon": "4833_1.png"
    },
    {
        "page": "4840_1",
        "type": "桌面类",
        "name": "家庭弹珠",
        "url": "4840_1.nes",
        "desc": "最多可4个玩家同时进行的家庭弹珠台nes游戏，有4个不同的弹珠台供玩家选择。",
        "icon": "4840_1.png"
    },
    {
        "page": "4836_1",
        "type": "桌面类",
        "name": "1999-Hore Mitakotoka 世纪末",
        "url": "4836_1.nes",
        "desc": "以某个世纪末地球出现危机为剧情的大富翁类nes游戏，nes游戏开始前要选择发型和脸型，图片不停的变换，按选择键停下。有4个角色，如果玩家只有一个，那么剩下的3个角色由电脑代替。",
        "icon": "4836_1.png"
    },
    {
        "page": "4837_1",
        "type": "桌面类",
        "name": "人生角色扮演游戏",
        "url": "4837_1.nes",
        "desc": "增加rpg内容的人生模拟nes游戏，有6个角色，角色不能选择只能根据剧情出现。",
        "icon": "4837_1.png"
    },
    {
        "page": "4839_1",
        "type": "桌面类",
        "name": "史上最强问答王决赛战",
        "url": "4839_1.nes",
        "desc": "模仿著名问答电视节目的nes游戏。支持6个玩家。nes游戏中有很多问题，玩家根据自己所知的来选择正确答案。",
        "icon": "4839_1.png"
    },
    {
        "page": "4838_1",
        "type": "桌面类",
        "name": "德比赌场-聚会房间21",
        "url": "4838_1.nes",
        "desc": "一个赌马的nes游戏，赛马开始前线选择一个要投注的马匹，选择好之后开始赛马比赛，比赛结束后如果投注的马匹跑了第一名，可以得到倍数的赌金，如果没有跑第一名，则没有任何赌金。",
        "icon": "4838_1.png"
    },
    {
        "page": "579_1",
        "type": "桌面类",
        "name": "消防站救援",
        "url": "579_1.nes",
        "desc": "一个以峡湾消防站主题的nes游戏,控制峡湾消防站的消防车到达目的地并扑灭大火.",
        "icon": "579_1.png"
    },
    {
        "page": "577_1",
        "type": "桌面类",
        "name": "小鬼当家",
        "url": "577_1.nes",
        "desc": "小鬼当家第一部，同名电影改编的休闲nes游戏，属于一款整蛊类型的游戏，想办法操控主人公小鬼利用各种道具严惩闯入家里的窃贼，游戏中还加入了一些解谜的元素。",
        "icon": "577_1.png"
    },
    {
        "page": "4854_1",
        "type": "桌面类",
        "name": "捍卫者的城市",
        "url": "4854_1.nes",
        "desc": "捍卫者的城市。",
        "icon": "4854_1.png"
    },
    {
        "page": "4853_1",
        "type": "桌面类",
        "name": "滑冰或死亡2",
        "url": "4853_1.nes",
        "desc": "滑冰的nes游戏，路上有很多障碍和其他滑冰者。",
        "icon": "4853_1.png"
    },
    {
        "page": "4852_1",
        "type": "桌面类",
        "name": "青蛙大冒险2 日版",
        "url": "4852_1.nes",
        "desc": "青蛙大冒险系列nes游戏第二部。",
        "icon": "4852_1.png"
    },
    {
        "page": "4851_1",
        "type": "桌面类",
        "name": "palamedes",
        "url": "4851_1.nes",
        "desc": "Palamedes方块nes游戏。",
        "icon": "4851_1.png"
    },
    {
        "page": "4850_1",
        "type": "桌面类",
        "name": "Hirake！Ponkikki",
        "url": "4850_1.nes",
        "desc": "Hirake！Ponkikki,nes游戏中有很多有趣的小nes游戏。",
        "icon": "4850_1.png"
    },
    {
        "page": "4849_1",
        "type": "桌面类",
        "name": "北极",
        "url": "4849_1.nes",
        "desc": "北极休闲nes游戏。",
        "icon": "4849_1.png"
    },
    {
        "page": "4848_1",
        "type": "桌面类",
        "name": "Q太郎-万万恐慌",
        "url": "4848_1.nes",
        "desc": "根据藤子不二雄的漫画代表作改编的nes游戏，玩家要帮助Q太郎躲开狗的攻击并吃完所有的道具，Q太郎可以飞起来，不过蓝色的能量消耗完之后就不能飞了。",
        "icon": "4848_1.png"
    },
    {
        "page": "4844_1",
        "type": "桌面类",
        "name": "企鹅战争",
        "url": "4844_1.nes",
        "desc": "玩家将操控一只企鹅进行投球nes游戏，nes游戏开始前双方的球数量是一样的，nes游戏开始后把球一个一个的投到对面，你在投球的时候对方也在向你这边投，这样看谁先把自己的球全部投到对面，被投过来的球击中后会短暂的倒下，每次都有时间限制，时间结束后球数量少的一方胜出。",
        "icon": "4844_1.png"
    },
    {
        "page": "4843_1",
        "type": "桌面类",
        "name": "迷你乐一通卡通工作室",
        "url": "4843_1.nes",
        "desc": "通过这个nes游戏可以自己设计兔八哥的动画.",
        "icon": "4843_1.png"
    },
    {
        "page": "4842_1",
        "type": "桌面类",
        "name": "史上最强问答王决赛战2",
        "url": "4842_1.nes",
        "desc": "问答王nes游戏第二部,增加了答题时的计时,有三种问答模式,可以自己选择参加的人数,最多支持6个人,共有6个参赛区域.",
        "icon": "4842_1.png"
    },
    {
        "page": "4870_1",
        "type": "桌面类",
        "name": "幸运之轮",
        "url": "4870_1.nes",
        "desc": "幸运之轮。",
        "icon": "4870_1.png"
    },
    {
        "page": "4867_1",
        "type": "桌面类",
        "name": "扣人心弦",
        "url": "4867_1.nes",
        "desc": "一位探险家在冰雪之地冒险的故事，站着按B键是出拳，跳起来按B键则是出褪。中间是不能停下来的，停下来超过10秒会因为寒冷开始减血，一会儿就挂了。",
        "icon": "4867_1.png"
    },
    {
        "page": "4865_1",
        "type": "桌面类",
        "name": "横冲直撞",
        "url": "4865_1.nes",
        "desc": "横冲直撞。",
        "icon": "4865_1.png"
    },
    {
        "page": "4863_1",
        "type": "桌面类",
        "name": "Hatris方块",
        "url": "4863_1.nes",
        "desc": "和俄罗斯方块差不多的nes游戏规则，多个方块重叠在一起即可消除。",
        "icon": "4863_1.png"
    },
    {
        "page": "4861_1",
        "type": "桌面类",
        "name": "陀螺机器人",
        "url": "4861_1.nes",
        "desc": "吃完地图中的道具就算过关，除了有很多泡泡龙一样的怪物追赶，还有很多炸弹也不能碰到。",
        "icon": "4861_1.png"
    },
    {
        "page": "4860_1",
        "type": "桌面类",
        "name": "科瑞斯特的乐趣屋",
        "url": "4860_1.nes",
        "desc": "马戏团里的动物逃跑了，玩家要帮助主人公要想尽一切办法把它们找回来。",
        "icon": "4860_1.png"
    },
    {
        "page": "4859_1",
        "type": "桌面类",
        "name": "罗罗冒险3",
        "url": "4859_1.nes",
        "desc": "大地图上有很多关卡，可以自己选择进入。。",
        "icon": "4859_1.png"
    },
    {
        "page": "4857_1",
        "type": "桌面类",
        "name": "迷宫",
        "url": "4857_1.nes",
        "desc": "在类似迷宫的地图中探险的nes游戏，怪物多半是些昆虫之类的，有时间限制。",
        "icon": "4857_1.png"
    },
    {
        "page": "4856_1",
        "type": "桌面类",
        "name": "神风超级玛丽2",
        "url": "4856_1.nes",
        "desc": "神风版超级玛丽2。",
        "icon": "4856_1.png"
    },
    {
        "page": "4855_1",
        "type": "桌面类",
        "name": "洛克人5-新的野心",
        "url": "4855_1.nes",
        "desc": "洛克人5-新的野心。",
        "icon": "4855_1.png"
    },
    {
        "page": "4886_1",
        "type": "桌面类",
        "name": "超级玛丽 超音鼠版",
        "url": "4886_1.nes",
        "desc": "超级玛丽超音鼠版,关卡和原版的超级玛丽美什么区别，把超级玛丽改成了超音鼠，怪物和道具等都改成了别的样子。",
        "icon": "4886_1.png"
    },
    {
        "page": "4885_1",
        "type": "桌面类",
        "name": "大沃尔历险",
        "url": "4885_1.nes",
        "desc": "大沃尔历险。",
        "icon": "4885_1.png"
    },
    {
        "page": "4884_1",
        "type": "桌面类",
        "name": "Klash Ball",
        "url": "4884_1.nes",
        "desc": "有三个队伍可以选择，有点像足球比赛，只是把赛场搬到了外太空的宇宙飞船上，球员换成了穿宇航服的星际勇士。",
        "icon": "4884_1.png"
    },
    {
        "page": "4883_1",
        "type": "桌面类",
        "name": "长手套2",
        "url": "4883_1.nes",
        "desc": "长手套nes游戏第二款。",
        "icon": "4883_1.png"
    },
    {
        "page": "4882_1",
        "type": "桌面类",
        "name": "古比管道大作战",
        "url": "4882_1.nes",
        "desc": "有方块不断的落下来，方块上都是些水管的图案，在落到地下之前可以变换方向，这和俄罗斯方块差不多，但是nes游戏规则并不一样，左右两边都是断开的管道，要利用方块中的水管通过变换方向使两边的管道连接在一起，最终使右边的水流到左边。在nes游戏的过程中左边有个名叫古比的男孩手中拿两面旗帜不停的助威。",
        "icon": "4882_1.png"
    },
    {
        "page": "4880_1",
        "type": "桌面类",
        "name": "诡秘的城堡",
        "url": "4880_1.nes",
        "desc": "诡秘的城堡。",
        "icon": "4880_1.png"
    },
    {
        "page": "4879_1",
        "type": "桌面类",
        "name": "超级玛丽 维特罗克版",
        "url": "4879_1.nes",
        "desc": "这个版本的超级玛丽无论从地图、怪物等方面与之前的大家玩过的超级玛丽都完全不一样，每过一关都可以自己选择下一关要过的关卡，快下载试试吧。",
        "icon": "4879_1.png"
    },
    {
        "page": "4877_1",
        "type": "桌面类",
        "name": "特罗格",
        "url": "4877_1.nes",
        "desc": "吃完地图中类似鸡蛋的道具即可过关，同时地下会不断的冒出怪物来。",
        "icon": "4877_1.png"
    },
    {
        "page": "4874_1",
        "type": "桌面类",
        "name": "雷电",
        "url": "4874_1.nes",
        "desc": "其实就是一个打砖块的nes游戏，挡板下面站着一个小孩，迅速的将挡板来回移动，有的方块打掉后有道具，比如挡板加长、增加球的数量、减慢球的移动速度等。雷电是伴有闪电和雷鸣的一种雄伟壮观而又有点令人生畏的放电现象。产生雷电的条件是雷雨云中有积累并形成极性。",
        "icon": "4874_1.png"
    },
    {
        "page": "4872_1",
        "type": "桌面类",
        "name": "仲义大作战",
        "url": "4872_1.nes",
        "desc": "仲义大作战。",
        "icon": "4872_1.png"
    },
    {
        "page": "4871_1",
        "type": "桌面类",
        "name": "唐老鸭故事2",
        "url": "4871_1.nes",
        "desc": "有3种nes游戏难度可以选择，共5个关卡，每次有3格血，nes游戏中有很多宝箱可以打开。",
        "icon": "4871_1.png"
    },
    {
        "page": "4914_1",
        "type": "桌面类",
        "name": "Kickle Cubicle 美版",
        "url": "4914_1.nes",
        "desc": "玩家要帮助主人公得到地图中的财宝，地图是断开的，敌人被攻击后就变成了冰块，把敌人变的冰块填补在断开的地方就可以过去了。",
        "icon": "4914_1.png"
    },
    {
        "page": "4907_1",
        "type": "桌面类",
        "name": "JJ-Tobidase大作战2",
        "url": "4907_1.nes",
        "desc": "玩家操控主人公不停的向前跑，躲开各种怪物。",
        "icon": "4907_1.png"
    },
    {
        "page": "4913_1",
        "type": "桌面类",
        "name": "花生与牛奶",
        "url": "4913_1.nes",
        "desc": "这个nes游戏可以自己选择关卡，主角是由花生和牛奶组成的Q版卡通人物。",
        "icon": "4913_1.png"
    },
    {
        "page": "4912_1",
        "type": "桌面类",
        "name": "阿斯特里克斯",
        "url": "4912_1.nes",
        "desc": "一个原始人冒险的故事，多国语言版，有多种语言可以选择。",
        "icon": "4912_1.png"
    },
    {
        "page": "4911_1",
        "type": "桌面类",
        "name": "BAD STREE brawler",
        "url": "4911_1.nes",
        "desc": "BAD STREE brawler。",
        "icon": "4911_1.png"
    },
    {
        "page": "4908_1",
        "type": "桌面类",
        "name": "命运之轮-家庭版",
        "url": "4908_1.nes",
        "desc": "转轮台的nes游戏。",
        "icon": "4908_1.png"
    },
    {
        "page": "4904_1",
        "type": "桌面类",
        "name": "家庭训练者-来来大冒险",
        "url": "4904_1.nes",
        "desc": "一位道长带着3个僵尸在过桥的时候，其中一个小僵尸不小心跌进了桥下的河里，被河水冲到了岸边，于是小僵尸开始了冒险。",
        "icon": "4904_1.png"
    },
    {
        "page": "4905_1",
        "type": "桌面类",
        "name": "摩艾君 日版",
        "url": "4905_1.nes",
        "desc": "以石猴摩艾君为主人公的益智nes游戏。",
        "icon": "4905_1.png"
    },
    {
        "page": "4903_1",
        "type": "桌面类",
        "name": "保护婴儿",
        "url": "4903_1.nes",
        "desc": "一个婴儿在路上一直向前爬，路上有奶瓶、元宝等，树上不时有猫出现，草丛里有蛇，以及各种障碍，控制屏幕上的十字瞄准这些障碍射击，清除障碍保护婴儿向前爬。到了没有桥的悬崖，要射击天空中的云朵，云朵里会掉下来冰块，婴儿就可以爬过去了。",
        "icon": "4903_1.png"
    },
    {
        "page": "4902_1",
        "type": "桌面类",
        "name": "Puzslot",
        "url": "4902_1.nes",
        "desc": "一款方块nes游戏，一次落下来两个连在一起的方块，在落下来的过程中图案也在不断的变换，需要把相同图案的方块重叠在一起，重叠在一起的相同图案的方块超过3个或者3个即可消除。",
        "icon": "4902_1.png"
    },
    {
        "page": "4901_1",
        "type": "桌面类",
        "name": "挖金锦标赛",
        "url": "4901_1.nes",
        "desc": "这是挖金小nes游戏的另一个版本，一共50个关卡，在nes游戏开始之前玩家可以自己选择进行的关卡。",
        "icon": "4901_1.png"
    },
    {
        "page": "4898_1",
        "type": "桌面类",
        "name": "魔术方块",
        "url": "4898_1.nes",
        "desc": "画面中有很多管道，中间有部分是断开的，需要将他们拼接好，有个球体顺着管道向前滚动，顺利通过所有管道则游戏胜利。",
        "icon": "4898_1.png"
    },
    {
        "page": "4896_1",
        "type": "桌面类",
        "name": "我还记得",
        "url": "4896_1.nes",
        "desc": "考验记忆能力的nes游戏。歌曲《我还记得》选自梁静茹专辑《丝路 通往爱的路途》，黄婷作词，易桀齐 伍冠谚 作曲，2005年滚石唱片出版并发行。",
        "icon": "4896_1.png"
    },
    {
        "page": "4917_1",
        "type": "桌面类",
        "name": "益智方块",
        "url": "4917_1.nes",
        "desc": "主要是通过移动方块过关，先按住B键不放，然后再按方向就可以随意移动方块了。",
        "icon": "4917_1.png"
    },
    {
        "page": "4916_1",
        "type": "桌面类",
        "name": "大眼蛙方块",
        "url": "4916_1.nes",
        "desc": "大眼蛙方块。",
        "icon": "4916_1.png"
    },
    {
        "page": "4915_1",
        "type": "桌面类",
        "name": "城堡冒险",
        "url": "4915_1.nes",
        "desc": "在城堡中冒险.",
        "icon": "4915_1.png"
    },
    {
        "page": "4890_1",
        "type": "桌面类",
        "name": "皮克-A-釜 扑克",
        "url": "4890_1.nes",
        "desc": "玩扑克的nes游戏，游戏开始前有3个美女可以选择最为对手。",
        "icon": "4890_1.png"
    },
    {
        "page": "4889_1",
        "type": "桌面类",
        "name": "兔子巴比-疯狂的城堡",
        "url": "4889_1.nes",
        "desc": "兔子巴比第二部之疯狂的城堡。",
        "icon": "4889_1.png"
    },
    {
        "page": "4937_1",
        "type": "桌面类",
        "name": "palamedes2",
        "url": "4937_1.nes",
        "desc": "帮助一个男孩不停的消除塔下面的方块，下面的方块会不停的加高。",
        "icon": "4937_1.png"
    },
    {
        "page": "4943_1",
        "type": "桌面类",
        "name": "诺伊达溜溜球兔",
        "url": "4943_1.nes",
        "desc": "主角是个会扔溜溜球的兔子，同时也是用溜溜球攻击敌人。",
        "icon": "4943_1.png"
    },
    {
        "page": "4941_1",
        "type": "桌面类",
        "name": "汉堡时代 美版",
        "url": "4941_1.nes",
        "desc": "汉堡时代 美版。",
        "icon": "4941_1.png"
    },
    {
        "page": "4940_1",
        "type": "桌面类",
        "name": "星际迷航",
        "url": "4940_1.nes",
        "desc": "3名主人公来到一个陌生且充满危险的星球执行任务。",
        "icon": "4940_1.png"
    },
    {
        "page": "4939_1",
        "type": "桌面类",
        "name": "peepar time",
        "url": "4939_1.nes",
        "desc": "nes游戏里面的主角只会不停的向目标跳动，玩家通过移动方块帮助主角顺利的到达目的地。",
        "icon": "4939_1.png"
    },
    {
        "page": "4938_1",
        "type": "桌面类",
        "name": "人质",
        "url": "4938_1.nes",
        "desc": "在一次突发事件中，警方出动警察、特警、狙击手等数百名解决人质，而玩家则扮演警方的指挥人员，最终能否成功救出人质，全部掌握在玩家的手中。",
        "icon": "4938_1.png"
    },
    {
        "page": "4936_1",
        "type": "桌面类",
        "name": "疯狂的石头",
        "url": "4936_1.nes",
        "desc": "控制一个石头到达终点的nes游戏，石头的惯性很大，而且地形已很糟糕，所以控制起来又点难度，从第二关开始还会有可以动的障碍物。",
        "icon": "4936_1.png"
    },
    {
        "page": "4934_1",
        "type": "桌面类",
        "name": "mappy-land",
        "url": "4934_1.nes",
        "desc": "主角是个大耳朵的老鼠，要躲开猫的追赶，吃完道具就可以过关了，最关键的时候还可以使用武器，不过武器只能同时使用一次。",
        "icon": "4934_1.png"
    },
    {
        "page": "4932_1",
        "type": "桌面类",
        "name": "泡沫洗浴宝贝",
        "url": "4932_1.nes",
        "desc": "nes游戏规则类似经典的泡泡龙，背景是一个正在洗浴的美女，从美女身上冒出来五颜六色的泡沫，玩家要操控这些泡沫以达到消除的目的。",
        "icon": "4932_1.png"
    },
    {
        "page": "4931_1",
        "type": "桌面类",
        "name": "hatris",
        "url": "4931_1.nes",
        "desc": "nes游戏规则类似俄罗斯方块，只是落下来的不是方块，而是各种各样的帽子，并且一次落下来两个，多个一样的帽子重叠在一起就可以消除。",
        "icon": "4931_1.png"
    },
    {
        "page": "4930_1",
        "type": "桌面类",
        "name": "平行世界",
        "url": "4930_1.nes",
        "desc": "天空中突然出现一个巨大的黑洞，将主角两人吸了进去。。。。接着nes游戏开始了。",
        "icon": "4930_1.png"
    },
    {
        "page": "4928_1",
        "type": "桌面类",
        "name": "印第安那琼斯与毁灭战士",
        "url": "4928_1.nes",
        "desc": "印第安那琼斯与毁灭战士。",
        "icon": "4928_1.png"
    },
    {
        "page": "4927_1",
        "type": "桌面类",
        "name": "地底冒险",
        "url": "4927_1.nes",
        "desc": "一共14个关卡，每个关卡有4层，找到每层的出口即可过关。",
        "icon": "4927_1.png"
    },
    {
        "page": "4948_1",
        "type": "桌面类",
        "name": "route-16",
        "url": "4948_1.nes",
        "desc": "在迷宫里躲避汽车的追赶。",
        "icon": "4948_1.png"
    },
    {
        "page": "4947_1",
        "type": "桌面类",
        "name": "神风超级玛丽",
        "url": "4947_1.nes",
        "desc": "神风版的超级玛丽。",
        "icon": "4947_1.png"
    },
    {
        "page": "4926_1",
        "type": "桌面类",
        "name": "Hudson Hawk",
        "url": "4926_1.nes",
        "desc": "玩家要帮助哈德森从美术馆里偷出达芬奇的名画，过程中不能被狮子发现，不然就会被扔到楼下面去。",
        "icon": "4926_1.png"
    },
    {
        "page": "4925_1",
        "type": "桌面类",
        "name": "Rod Land",
        "url": "4925_1.nes",
        "desc": "为了拯救被敌人绑架的母亲，莉特和塔姆展开了探险，打败敌人后可以得到积分和道具。",
        "icon": "4925_1.png"
    },
    {
        "page": "4923_1",
        "type": "桌面类",
        "name": "逃亡 4.0版",
        "url": "4923_1.nes",
        "desc": "从危险重重的环境中逃出去。《逃亡》是新加坡女歌手孙燕姿于2001.07.09发表的第3张个人专辑《风筝》中第04首歌曲。",
        "icon": "4923_1.png"
    },
    {
        "page": "4921_1",
        "type": "桌面类",
        "name": "罗罗冒险",
        "url": "4921_1.nes",
        "desc": "主角罗罗要通过推开箱子，吃到所有的心状道具,里面的敌人直接是推不动的，如果又武器才可以推动。",
        "icon": "4921_1.png"
    },
    {
        "page": "4918_1",
        "type": "桌面类",
        "name": "面包超人",
        "url": "4918_1.nes",
        "desc": "明娜者徒步旅行nes游戏.",
        "icon": "4918_1.png"
    },
    {
        "page": "4959_1",
        "type": "桌面类",
        "name": "点子游戏",
        "url": "4959_1.nes",
        "desc": "我玩了几次也没弄明白nes游戏规则,你们来试试吧.",
        "icon": "4959_1.png"
    },
    {
        "page": "4966_1",
        "type": "桌面类",
        "name": "地铁交叉",
        "url": "4966_1.nes",
        "desc": "在地面上不断向前奔跑，要躲开各种障碍，躲不开可以跳起来。",
        "icon": "4966_1.png"
    },
    {
        "page": "4964_1",
        "type": "桌面类",
        "name": "怒ikari",
        "url": "4964_1.nes",
        "desc": "主人公乘坐的战斗机在途中坠毁，不得不与敌人展开战斗突破敌人防线。",
        "icon": "4964_1.png"
    },
    {
        "page": "4963_1",
        "type": "桌面类",
        "name": "亚当斯家族",
        "url": "4963_1.nes",
        "desc": "刚开始好像没有武器，跳起来踩到敌人的上面就可以把敌人消灭掉，中间还要躲开敌人发射的子弹。",
        "icon": "4963_1.png"
    },
    {
        "page": "4961_1",
        "type": "桌面类",
        "name": "凯蒂猫世界",
        "url": "4961_1.nes",
        "desc": "开出来凯蒂猫身上有两个气球，可以飞起来，沿途上空会飘有很多气球，凯蒂猫只要碰到气球，气球就会爆炸，而凯蒂猫的任务就是将这些气球都搞破，注意不能碰到下面的火堆，不然就成烤猫了。",
        "icon": "4961_1.png"
    },
    {
        "page": "4960_1",
        "type": "桌面类",
        "name": "粉碎",
        "url": "4960_1.nes",
        "desc": "与敌人展开激烈的枪战。",
        "icon": "4960_1.png"
    },
    {
        "page": "4957_1",
        "type": "桌面类",
        "name": "忍者龙剑传3 汉化版",
        "url": "4957_1.nes",
        "desc": "所有的内容都已经汉化,不再为看不懂游戏中的文字而烦恼.。",
        "icon": "4957_1.png"
    },
    {
        "page": "4956_1",
        "type": "桌面类",
        "name": "小鬼当家2-迷失纽约",
        "url": "4956_1.nes",
        "desc": "著名电影改编的nes游戏第二部.",
        "icon": "4956_1.png"
    },
    {
        "page": "4954_1",
        "type": "桌面类",
        "name": "耀奇之神奇蛋仔 中文版",
        "url": "4954_1.nes",
        "desc": "将俄罗斯方块和超级玛丽结合在一起的nes游戏,移动掉下来的图案并使其消失,两个相同的图案在一起的时候就会消失.",
        "icon": "4954_1.png"
    },
    {
        "page": "4953_1",
        "type": "桌面类",
        "name": "低重力战士",
        "url": "4953_1.nes",
        "desc": "该nes游戏以未来战争为题材的nes游戏。",
        "icon": "4953_1.png"
    },
    {
        "page": "4952_1",
        "type": "桌面类",
        "name": "热血道中记",
        "url": "4952_1.nes",
        "desc": "以日本古代为nes游戏背景，除了可以使用拳和脚攻击，还可以使用必杀技",
        "icon": "4952_1.png"
    },
    {
        "page": "4951_1",
        "type": "桌面类",
        "name": "田代魔界冒险",
        "url": "4951_1.nes",
        "desc": "为了救出4位公主而进入魔界冒险。",
        "icon": "4951_1.png"
    },
    {
        "page": "4950_1",
        "type": "桌面类",
        "name": "星之卡比冒险",
        "url": "4950_1.nes",
        "desc": "红白机很受欢迎的一款nes游戏，刚出来从中间那个们出去，然后冒险就正式开始了，主角可以把敌人吸到自己的肚子里，然后再像子弹一样把敌人发射出去。",
        "icon": "4950_1.png"
    },
    {
        "page": "4974_1",
        "type": "桌面类",
        "name": "股票道场",
        "url": "4974_1.nes",
        "desc": "有5种经营型模拟的nes游戏,第一个是模拟炒股的项目,初始金钱是1000万.",
        "icon": "4974_1.png"
    },
    {
        "page": "4973_1",
        "type": "桌面类",
        "name": "有趣的方块",
        "url": "4973_1.nes",
        "desc": "有趣的方块nes游戏,经过汉化的.",
        "icon": "4973_1.png"
    },
    {
        "page": "4972_1",
        "type": "桌面类",
        "name": "射击方块 日文版",
        "url": "4972_1.nes",
        "desc": "射击方块 日文版。，",
        "icon": "4972_1.png"
    },
    {
        "page": "4969_1",
        "type": "桌面类",
        "name": "MAPPY",
        "url": "4969_1.nes",
        "desc": "猫和老鼠的nes游戏。",
        "icon": "4969_1.png"
    },
    {
        "page": "4967_1",
        "type": "桌面类",
        "name": "狐狸小飞侠-海盗",
        "url": "4967_1.nes",
        "desc": "狐狸小飞侠-海盗。",
        "icon": "4967_1.png"
    },
    {
        "page": "4949_1",
        "type": "桌面类",
        "name": "长手套",
        "url": "4949_1.nes",
        "desc": "长手套。",
        "icon": "4949_1.png"
    },
    {
        "page": "4992_1",
        "type": "桌面类",
        "name": "家庭五子棋(奥赛罗棋)",
        "url": "4992_1.nes",
        "desc": "可设定nes游戏难度，也可二人对战的黑白棋nes游戏。",
        "icon": "4992_1.png"
    },
    {
        "page": "4998_1",
        "type": "桌面类",
        "name": "赌神(美版)",
        "url": "4998_1.nes",
        "desc": "桌棋类型的冒险RPG节目。共有4位角色登场。最终目的是锻炼成为伟大的勇者并拯救赛兰多王国。可惜的是找不到中文版，相信大家可能都玩过它的中文版吧，玩玩原版试试。",
        "icon": "4998_1.png"
    },
    {
        "page": "4996_1",
        "type": "桌面类",
        "name": "将棋名鉴’93",
        "url": "4996_1.nes",
        "desc": "设有5种对局模式的将棋nes游戏，收有95局棋谱。",
        "icon": "4996_1.png"
    },
    {
        "page": "4994_1",
        "type": "桌面类",
        "name": "RPG人生游戏",
        "url": "4994_1.nes",
        "desc": "由著名桌棋nes游戏加入RPG要素的强化版。设有6种职业可选择，剧情会随所选职业而异。",
        "icon": "4994_1.png"
    },
    {
        "page": "4993_1",
        "type": "桌面类",
        "name": "赌神",
        "url": "4993_1.nes",
        "desc": "桌棋类型的冒险RPG节目。共有4位角色登场。最终目的是锻炼成为伟大的勇者并拯救赛兰多王国。可惜的是找不到中文版，相信大家可能都玩过它的中文版吧，玩玩原版试试。",
        "icon": "4993_1.png"
    },
    {
        "page": "4997_1",
        "type": "桌面类",
        "name": "爆笑四天王",
        "url": "4997_1.nes",
        "desc": "爆笑四天王。",
        "icon": "4997_1.png"
    },
    {
        "page": "4984_1",
        "type": "桌面类",
        "name": "小尼莫-主人的铰",
        "url": "4984_1.nes",
        "desc": "一个还未断奶的小男孩在森林冒险的nes游戏。小男孩的武器是糖果，糖果不能消灭敌人的，只能让怪物短暂昏迷。有些怪物是可以吃糖果，吃三颗后就会睡觉，然后小男孩就变成其模样，拥有怪物的能力。",
        "icon": "4984_1.png"
    },
    {
        "page": "4988_1",
        "type": "桌面类",
        "name": "荷里活广场",
        "url": "4988_1.nes",
        "desc": "站在中间的主持人会说一段详细的描述，然后根据描述在9个人物中描择出正确的一个。",
        "icon": "4988_1.png"
    },
    {
        "page": "4987_1",
        "type": "桌面类",
        "name": "流行小宠物",
        "url": "4987_1.nes",
        "desc": "主角是个黄色的小宠物，样子很可爱，在墙的下面吊有茧一样的东西，nes游戏开始一段时间后就会从茧里面出来鲨鱼一样的怪物，可以用炸弹炸掉，主角可以在地面上走，也可以倒着走，任务是得到笼中的红色桃心，当把困住红色桃心的笼子炸开后，红心会飞到最上面，需要消灭拦路的敌人，才可以到上面去。",
        "icon": "4987_1.png"
    },
    {
        "page": "4982_1",
        "type": "桌面类",
        "name": "3D球体",
        "url": "4982_1.nes",
        "desc": "被称之为克罗恩的邪恶精灵危及整个银河的安全，银河星系的命运掌握在你的手中...",
        "icon": "4982_1.png"
    },
    {
        "page": "4981_1",
        "type": "桌面类",
        "name": "深入地下城",
        "url": "4981_1.nes",
        "desc": "是在一个3D迷宫中探险的nes游戏。迷宫中有很多房间，进入房间会有人和你对话： leave(离开)、talk(谈话，得到线索)、search(调查)、gear(机关)、kill（攻击）...",
        "icon": "4981_1.png"
    },
    {
        "page": "4983_1",
        "type": "桌面类",
        "name": "男孩和他的雪人",
        "url": "4983_1.nes",
        "desc": "一个背着书包的学生，身边跟了一个雪人朋友，这个学生走到哪里，学生就跟到哪里。如果跑的太快，雪人跟不上，按下B键雪人就会瞬间出现在旁边，给雪人喂一个水滴，雪人就会变成梯子。",
        "icon": "4983_1.png"
    },
    {
        "page": "4980_1",
        "type": "桌面类",
        "name": "遮阳伞小子",
        "url": "4980_1.nes",
        "desc": "一个男孩靠一把遮阳伞闯荡森林的nes游戏，有一半的敌人都不会主动攻击。地上有水坑的地方可以跳起来打开遮阳伞，这样会跳的更远，要是想快速通关可以不用打怪物，直接往前跑。",
        "icon": "4980_1.png"
    },
    {
        "page": "4979_1",
        "type": "桌面类",
        "name": "辛普森一家-巴特与世界",
        "url": "4979_1.nes",
        "desc": "该nes游戏是由几个小nes游戏组成，第一个是一个男孩在海盗船上冒险的nes游戏，第二个是拼图nes游戏，第三个是纸牌nes游戏。",
        "icon": "4979_1.png"
    },
    {
        "page": "4977_1",
        "type": "桌面类",
        "name": "莱恩和史丁比",
        "url": "4977_1.nes",
        "desc": "猫和狗之间nes游戏。刚开始在一个家里面，猫可以吐出小球来消灭障碍，前面有一个传送机，猫走上去就被传送到了外太空，开始了空战nes游戏。",
        "icon": "4977_1.png"
    },
    {
        "page": "4976_1",
        "type": "桌面类",
        "name": "圈苹果 日版",
        "url": "4976_1.nes",
        "desc": "在地图中有很多个方格子，在红色的格子中会随机出现一个苹果，主角拉着一根绳子过去围着有苹果的方格子转一圈，将方格子用绳子围起来，苹果被围起来后方格子出现生气的表情，如果苹果长时间没有被围住就会变到另一个方格子中。所有的放鸽子都变成生气的表情则nes游戏胜利。",
        "icon": "4976_1.png"
    },
    {
        "page": "4975_1",
        "type": "桌面类",
        "name": "小猪推箱子",
        "url": "4975_1.nes",
        "desc": "这个nes游戏的规则和别的nes游戏推箱子略有不同。主角是一只小猪，而箱子用麻将代替。",
        "icon": "4975_1.png"
    },
    {
        "page": "5017_1",
        "type": "桌面类",
        "name": "花式撞球(日版)",
        "url": "5017_1.nes",
        "desc": "著名的台球nes游戏，包括9球模式及正统模式。可二人对战。",
        "icon": "5017_1.png"
    },
    {
        "page": "5018_1",
        "type": "桌面类",
        "name": "雀豪",
        "url": "5018_1.nes",
        "desc": "本节目是正统的四人麻将。nes游戏中设有玩者的姓名登录系统，最多可登录16人。",
        "icon": "5018_1.png"
    },
    {
        "page": "5016_1",
        "type": "桌面类",
        "name": "自我中心派2麻将",
        "url": "5016_1.nes",
        "desc": "由个人电脑版移植的麻将节目续作。与前作同样有3种模式，24位角色，并设有nes游戏评定系统。",
        "icon": "5016_1.png"
    },
    {
        "page": "5014_1",
        "type": "桌面类",
        "name": "家庭将棋龙王战",
        "url": "5014_1.nes",
        "desc": "设有3种模式的将棋节目。可自己设定棋士进行nes游戏。",
        "icon": "5014_1.png"
    },
    {
        "page": "5010_1",
        "type": "桌面类",
        "name": "东风-中国麻将",
        "url": "5010_1.nes",
        "desc": "以中国为舞台的麻将nes游戏。主人公是一名少年雀士，为解救被困的妹妹而挑战各地的麻将高手，nes游戏中可使用必杀牌及天神自摸等超能力。",
        "icon": "5010_1.png"
    },
    {
        "page": "5008_1",
        "type": "桌面类",
        "name": "月宫桌球(中文)",
        "url": "5008_1.nes",
        "desc": "月宫桌球(中文)。",
        "icon": "5008_1.png"
    },
    {
        "page": "5007_1",
        "type": "桌面类",
        "name": "本将棋内藤九段将棋秘传",
        "url": "5007_1.nes",
        "desc": "设有12种方式的将棋节目。CPU思考时间较长。",
        "icon": "5007_1.png"
    },
    {
        "page": "5004_1",
        "type": "桌面类",
        "name": "4人麻将",
        "url": "5004_1.nes",
        "desc": "正统派4人麻将nes游戏。内容十分单纯。",
        "icon": "5004_1.png"
    },
    {
        "page": "5023_1",
        "type": "桌面类",
        "name": "围棋大战",
        "url": "5023_1.nes",
        "desc": "围棋大战。那些年我们一起玩过的游戏，童鞋们，你还记得小霸王里围棋大战吗，对就是围棋大战；是不是童年时被父母管着不让玩，一直想打通关有木有，现在它又来逆袭了。优质的画面，经典的旋律，经典的手柄键盘，一定会让你回到童年时代的记忆！",
        "icon": "5023_1.png"
    },
    {
        "page": "5022_1",
        "type": "桌面类",
        "name": "花札游戏",
        "url": "5022_1.nes",
        "desc": "花札nes游戏。花札（はなふだ），即花斗，又名花牌，花纸牌。一般两人玩的叫「こいこい(英文：Koi-Koi)」。据传，花札起源于日本安土（织田信长） ·桃山时代（丰臣秀吉），直到江户（德川家康）后期才最终定型成为现在的样子。甚至到现在连画的图案都没有什么变化，非常统一。",
        "icon": "5022_1.png"
    },
    {
        "page": "5021_1",
        "type": "桌面类",
        "name": "超级弹珠台",
        "url": "5021_1.nes",
        "desc": "加入麻雀要素的中国风格弹珠台节目。操作方法与普通弹珠节目相同。",
        "icon": "5021_1.png"
    },
    {
        "page": "5020_1",
        "type": "桌面类",
        "name": "AV麻雀俱乐部(完全版)",
        "url": "5020_1.nes",
        "desc": "此nes游戏为完全版，包含过关时的美女图片，原先提供的版本过关无图片。",
        "icon": "5020_1.png"
    },
    {
        "page": "5003_1",
        "type": "桌面类",
        "name": "Nes斗地主(锄大D)(斗地主明星版)",
        "url": "5003_1.nes",
        "desc": "锄大D(斗地主)(明星版)。",
        "icon": "5003_1.png"
    },
    {
        "page": "5001_1",
        "type": "桌面类",
        "name": "国际象棋",
        "url": "5001_1.nes",
        "desc": "国际象棋。",
        "icon": "5001_1.png"
    },
    {
        "page": "5000_1",
        "type": "桌面类",
        "name": "谷川浩司的将棋指南3",
        "url": "5000_1.nes",
        "desc": "谷川将棋的系列第三作。设有多种特殊模式可选择。",
        "icon": "5000_1.png"
    },
    {
        "page": "5029_1",
        "type": "桌面类",
        "name": "桃太郎电铁",
        "url": "5029_1.nes",
        "desc": "以桃太郎经营的铁路公司为中心展开的桌棋类节目。最多可四人同时进行nes游戏。",
        "icon": "5029_1.png"
    },
    {
        "page": "5036_1",
        "type": "桌面类",
        "name": "麻将大战",
        "url": "5036_1.nes",
        "desc": "初学者也可轻松进行的二人麻将nes游戏。设有类似于RPG的战胜对手即可升级的系统。",
        "icon": "5036_1.png"
    },
    {
        "page": "5034_1",
        "type": "桌面类",
        "name": "森田和太郎之将棋(森田棋)",
        "url": "5034_1.nes",
        "desc": "由森田和太郎监制的将棋nes游戏。共有三种难度可选择。",
        "icon": "5034_1.png"
    },
    {
        "page": "5033_1",
        "type": "桌面类",
        "name": "竞马赛场",
        "url": "5033_1.nes",
        "desc": "竞马赛场。《竞马OL》是由苏州争渡科技经过2年时间精心研发的国内首款3D赛马网游，在游戏同质化的今天，必定能给玩家带来耳目一新的感受。青茵的赛马场、坚实有力的马蹄，甚至骑手脸上的汗水，都可以看的清清楚楚，游戏借助强大的Gamebryo次时代引擎打造了一个逼真的赛马世界，让玩家饕餮一场视觉盛宴。同时又有内容丰富的马匹养成系统和深受女性玩家喜爱的庄园系统。在这里，你可以在马背上高歌飞扬，也可以在游乐场里闲情惬意；可以在俱乐部里与朋友煮酒论马，也可以与爱人在庄园里甜言蜜语。",
        "icon": "5033_1.png"
    },
    {
        "page": "5032_1",
        "type": "桌面类",
        "name": "家庭弹珠台",
        "url": "5032_1.nes",
        "desc": "可4人交替进行的弹珠节目。设有多种nes游戏模式及方法。",
        "icon": "5032_1.png"
    },
    {
        "page": "5030_1",
        "type": "桌面类",
        "name": "1999强手棋",
        "url": "5030_1.nes",
        "desc": "以世纪末地球危机为题材的桌棋冒险节目。nes游戏者要存储宇宙能量帮助地球摆脱各方面危机最多可4人同时进行。",
        "icon": "5030_1.png"
    },
    {
        "page": "5028_1",
        "type": "桌面类",
        "name": "BibleBuffet",
        "url": "5028_1.nes",
        "desc": "BibleBuffet。翻译过来应该是“圣经自助”，这意思真是奇葩。。《圣经》（希伯来语：ביבליה，拉丁语：Biblia，希腊语：Βιβλίο，英语：Bible俄语：библия（意为莎草纸）)，可以指犹太教和基督教（包括天主教、东正教和新教）的宗教经典，又译《耶经》。犹太教的宗教经典是指圣经《旧约》部分，即《塔纳赫》（或称希伯来《圣经》），而基督宗教的《圣经》则指《旧约》和《新约》两部分。犹太人的圣经《塔纳赫》从耶和华如何创世开始，然后讲述古时犹太人的历史，并记录先知预言。基督宗教的《新约圣经》记载耶稣基督和其门徒的言行，以及早期基督教的事件纪录、使徒保罗写给教会或其他人的书信、或其他使徒写给教会的书信，即神借着人手而写下他的话。圣经经历长时间的编辑、千年的翻译、流传，已形成专门的“释经学”。不同的基督教派别所承认的《圣经》旧约部分略有不同，天主教版本承认46卷，东正教版本承认50卷，基督新教版本承认39卷。《圣经》新约的书卷数比较一致，天主教、东正教、新教都承认27卷。在中国大陆，新教的和合本《圣经》人名地名等处理用英文音译的做法，天主教（思高圣经）《圣经》则采用拉丁文音译的做法，比如英文音译“彼得”，按拉丁文音译为“伯多禄”。圣经是西方文化的重要源泉，也是一部包罗万象的百科全书。它是世界上发行量最大，发行时间最长，翻译成的语言最多，流行最广而读者面最大，影响最深远的一部书，并已被列入吉尼斯世界纪录大全。",
        "icon": "5028_1.png"
    },
    {
        "page": "5027_1",
        "type": "桌面类",
        "name": "井出洋介名人的实战麻雀2",
        "url": "5027_1.nes",
        "desc": "由职业雀士的名人井出洋介担当制作顾问的麻雀节目之二。增加了RPG模式。",
        "icon": "5027_1.png"
    },
    {
        "page": "5026_1",
        "type": "桌面类",
        "name": "麻雀",
        "url": "5026_1.nes",
        "desc": "FC最早的麻雀节目。内容非常单纯。",
        "icon": "5026_1.png"
    },
    {
        "page": "5025_1",
        "type": "桌面类",
        "name": "四川麻将",
        "url": "5025_1.nes",
        "desc": "四川麻将。四川麻将，又称成都麻将，或血战麻将，流行于四川、重庆、贵州一带。其核心是打缺门，刮风下雨，计番，血战到底，流局查叫、查花猪。",
        "icon": "5025_1.png"
    }
]